untilperfect/__init__.py
untilperfect/__main__.py
untilperfect/cli.py
untilperfect/iotools.py
untilperfect/model.py
untilperfect/plots.py
untilperfect/pulptools.py
untilperfect-0.0.2.dist-info/LICENSE
untilperfect-0.0.2.dist-info/METADATA
untilperfect-0.0.2.dist-info/WHEEL
untilperfect-0.0.2.dist-info/entry_points.txt
untilperfect-0.0.2.dist-info/top_level.txt
untilperfect-0.0.2.dist-info/RECORD
