Metadata-Version: 2.1
Name: untilperfect
Version: 0.0.2
Summary: Solves the buffer preparation vessel sizing and assignment problem using mixed integer linear programming.
Home-page: https://github.com/multipitch/untilperfect
Author: Sean Tully
Author-email: sean.tully@ucdconnect.ie
License: UNKNOWN
Platform: UNKNOWN
Classifier: Development Status :: 3 - Alpha
Classifier: Environment :: Console
Classifier: License :: OSI Approved :: MIT License
Classifier: Operating System :: OS Independent
Classifier: Programming Language :: Python
Classifier: Programming Language :: Python :: 3.7
Classifier: Programming Language :: Python :: 3 :: Only
Requires-Dist: matplotlib (>=3.0.1)
Requires-Dist: numpy (>=1.15.4)
Requires-Dist: PuLP (>=1.6.9)
Requires-Dist: pylatexenc (>=1.3)
Provides-Extra: dev
Requires-Dist: black ; extra == 'dev'
Requires-Dist: pylint ; extra == 'dev'
Requires-Dist: sphinx ; extra == 'dev'
Requires-Dist: sphinxcontrib-svg2pdfconverter ; extra == 'dev'
